equilibrium/AdmissionController.py
equilibrium/BaseController.py
equilibrium/ControllerRegistry.py
equilibrium/CrudResourceController.py
equilibrium/JsonResourceStore.py
equilibrium/JsonResourceStore_test.py
equilibrium/Namespace.py
equilibrium/NotSet.py
equilibrium/Resource.py
equilibrium/ResourceContext.py
equilibrium/ResourceController.py
equilibrium/ResourceRegistry.py
equilibrium/ResourceStore.py
equilibrium/ResourceTypeRegistry.py
equilibrium/Resource_test.py
equilibrium/Service.py
equilibrium/ServiceRegistry.py
equilibrium/__init__.py
equilibrium/py.typed
equilibrium/types/FrozenDict.py
equilibrium/types/FrozenList.py
equilibrium/types/HashableMapping.py
equilibrium/types/HashableSequence.py
equilibrium/types/__init__.py
python_equilibrium-0.7.2.dist-info/LICENSE
python_equilibrium-0.7.2.dist-info/METADATA
python_equilibrium-0.7.2.dist-info/WHEEL
python_equilibrium-0.7.2.dist-info/RECORD
