Metadata-Version: 2.1
Name: python-equilibrium
Version: 0.7.2
Summary: 
License: MIT
Author: Niklas Rosenstein
Author-email: rosensteinniklas@gmail.com
Requires-Python: >=3.10,<4.0
Classifier: License :: OSI Approved :: MIT License
Classifier: Programming Language :: Python :: 3
Classifier: Programming Language :: Python :: 3.10
Classifier: Programming Language :: Python :: 3.11
Requires-Dist: databind.json (>=4.2.5,<5.0.0)
Requires-Dist: frozendict (>=2.3.8,<3.0.0)
Requires-Dist: pyyaml (>=6.0,<7.0)
Requires-Dist: types-pyyaml (>=6.0.12.9,<7.0.0.0)
Project-URL: Bug Tracker, https://github.com/NiklasRosenstein/python-equilibrium/issues
Project-URL: Homepage, https://github.com/NiklasRosenstein/python-equilibrium
Project-URL: Repository, https://github.com/NiklasRosenstein/python-equilibrium
